audreylab_summarypostqc/__init__.py
audreylab_summarypostqc/annotator.py
audreylab_summarypostqc/cli.py
audreylab_summarypostqc/plotting.py
audreylab_summarypostqc-0.1.2.dist-info/METADATA
audreylab_summarypostqc-0.1.2.dist-info/WHEEL
audreylab_summarypostqc-0.1.2.dist-info/entry_points.txt
audreylab_summarypostqc-0.1.2.dist-info/top_level.txt
audreylab_summarypostqc-0.1.2.dist-info/RECORD
