Metadata-Version: 2.4
Name: audreylab-summarypostqc
Version: 0.1.2
Summary: GWAS summary QC plotting tool (QQ & Manhattan plots)
Home-page: https://github.com/EtienneNtumba/audreylab-summarypostqc
Author: Etienne Kabongo
Author-email: Etienne Kabongo <etienne@example.com>
License: MIT
Project-URL: Homepage, https://github.com/EtienneNtumba/audreylab-summarypostqc
Project-URL: BugTracker, https://github.com/EtienneNtumba/audreylab-summarypostqc/issues
Requires-Python: >=3.7
Requires-Dist: pandas
Requires-Dist: numpy
Requires-Dist: matplotlib
Requires-Dist: seaborn
Requires-Dist: scipy
Requires-Dist: pybiomart
Requires-Dist: myvariant
Dynamic: author
Dynamic: home-page
Dynamic: requires-python
